binscheme_parser/__init__.py
binscheme_parser/data_structures.py
binscheme_parser/parser.py
binscheme_parser-0.0.1.dist-info/licenses/LICENSE
binscheme_parser-0.0.1.dist-info/METADATA
binscheme_parser-0.0.1.dist-info/WHEEL
binscheme_parser-0.0.1.dist-info/top_level.txt
binscheme_parser-0.0.1.dist-info/RECORD
