Metadata-Version: 2.4
Name: binscheme-parser
Version: 0.0.1
Summary: A parser for the binScheme language, a declarative language for defining binary data layouts.
Author-email: kazakan <dojh99@google.com>
License: 
Project-URL: Homepage, https://github.com/kazakan/binscheme
Project-URL: Bug Tracker, https://github.com/kazakan/binscheme/issues
Classifier: Development Status :: 3 - Alpha
Classifier: Intended Audience :: Developers
Classifier: Topic :: Software Development :: Compilers
Classifier: Programming Language :: Python :: 3
Classifier: License :: OSI Approved :: MIT License
Classifier: Operating System :: OS Independent
Requires-Python: >=3.8
License-File: LICENSE
Requires-Dist: lark>=1.0
Dynamic: license-file
